get_book_sales_ranking/main.py
get_book_sales_ranking/api/google_api.py
get_book_sales_ranking/api/opendb_api.py
get_book_sales_ranking/api/opensearch_api.py
get_book_sales_ranking/api/rakuten_api.py
get_book_sales_ranking/api/sru_api.py
get_book_sales_ranking/data_fix/clean_up.py
get_book_sales_ranking/data_fix/fix_isbn.py
get_book_sales_ranking/data_fix/matome_jikkou.py
get_book_sales_ranking/ranking/booklog/booklog_ranking.py
get_book_sales_ranking/ranking/booklog/week_url.py
get_book_sales_ranking/ranking/bookmeter/bookmeter_individual.py
get_book_sales_ranking/ranking/bookmeter/bookmeter_ranking.py
get_book_sales_ranking/ranking/bookoff/bookoff_individual.py
get_book_sales_ranking/ranking/bookoff/bookoff_ranking.py
get_book_sales_ranking-0.1.11.dist-info/LICENSE
get_book_sales_ranking-0.1.11.dist-info/METADATA
get_book_sales_ranking-0.1.11.dist-info/WHEEL
get_book_sales_ranking-0.1.11.dist-info/entry_points.txt
get_book_sales_ranking-0.1.11.dist-info/top_level.txt
get_book_sales_ranking-0.1.11.dist-info/RECORD
